{
    "context": "client",
    "identifier": "uk.pa.tetcmappack",
    "display_name": "TheEffectTheCause's Map Pack",
    "description": "Wierd, Wonderful and damn right crazy maps for all your PA needs. A variety of maps with differing styles for all types of play. Update: New Map - Fortress for 3v3v3v3 unshared team game's",
    "author": "TheEffectTheCause",
    "version": "3.2.3",
    "build": "108271",
    "date": "2020/04/29",
    "signature": "not yet implemented",
    "forum": "https://forums.planetaryannihilation.com/threads/theeffectthecause-map-pack.73439/",
    "icon": "https://i.imgur.com/iERzQ3v.jpg",
    "category": [
        "maps"
    ],
    "load_planet": [
        "coui://ui/mods/tetcmp1/maplist.js"
    ],
    "searchable": [
        "theeffectthecause",
        "pack",
        "maps",
        "planet"
    ],
    "priority": 100,
    "enabled": true,
    "dependencies": [
        "com.pa.conundrum.cShareSystems",
	"uk.pa.tetctree",
	"uk.pa.tetctree.server"
    ],
	    "framework": false,
    "available": true,
    "titansOnly": false,
    "classicOnly": false,
    "classic": false,
    "titans": false
}
